[
  {
    "id": "CARLA_SILVA",
    "nome": "CARLA SILVA",
    "classe": "Aframax",
    "ibe": 50.8,
    "ibeMedio": 40.6,
    "consumoReal": 60.3,
    "consumoIdeal": 40,
    "deltaFuelNm": 20.31,
    "emissoesCO2Perdidas": 23394.0,
    "riscoNormam401": "Critico",
    "statusOperacional": "Atracado",
    "diasDesdeUltimaLimpeza": 1736,
    "posicaoAtual": {
      "latitude": -23.04877,
      "longitude": -43.12019,
      "velocidade": 0.1,
      "rumo": 137.0,
      "dataHora": "2025-11-24 22:24:18"
    },
    "recomendacao": "Limpeza Imediata",
    "economiaAnual": 40207672.0,
    "eventosCriticos": 8,
    "eventosAlto": 15,
    "viagensAnalisadas": 30,
    "previsao30d": 51.6,
    "previsao60d": 52.5,
    "previsao90d": 53.4
  },
  {
    "id": "PAULO_MOURA",
    "nome": "PAULO MOURA",
    "classe": "Suezmax",
    "ibe": 46.1,
    "ibeMedio": 36.9,
    "consumoReal": 58.4,
    "consumoIdeal": 40,
    "deltaFuelNm": 18.44,
    "emissoesCO2Perdidas": 21243.0,
    "riscoNormam401": "Critico",
    "statusOperacional": "Navegando",
    "diasDesdeUltimaLimpeza": 1732,
    "posicaoAtual": {
      "latitude": -26.855831,
      "longitude": -40.025448,
      "velocidade": 11.4,
      "rumo": 102.6,
      "dataHora": "2025-09-01 12:50:17"
    },
    "recomendacao": "Limpeza Imediata",
    "economiaAnual": 36512009.0,
    "eventosCriticos": 7,
    "eventosAlto": 13,
    "viagensAnalisadas": 30,
    "previsao30d": 46.9,
    "previsao60d": 47.7,
    "previsao90d": 48.5
  },
  {
    "id": "HENRIQUE_ALVES",
    "nome": "HENRIQUE ALVES",
    "classe": "Suezmax",
    "ibe": 35.8,
    "ibeMedio": 28.7,
    "consumoReal": 54.3,
    "consumoIdeal": 40,
    "deltaFuelNm": 14.33,
    "emissoesCO2Perdidas": 16511.0,
    "riscoNormam401": "Critico",
    "statusOperacional": "Atracado",
    "diasDesdeUltimaLimpeza": 1465,
    "posicaoAtual": {
      "latitude": -23.136715,
      "longitude": -44.467988,
      "velocidade": 0.0,
      "rumo": 27.6,
      "dataHora": "2025-11-24 20:11:30"
    },
    "recomendacao": "Limpeza Imediata",
    "economiaAnual": 28377885.0,
    "eventosCriticos": 5,
    "eventosAlto": 10,
    "viagensAnalisadas": 30,
    "previsao30d": 36.6,
    "previsao60d": 37.3,
    "previsao90d": 38.0
  },
  {
    "id": "MARIA_VALENTINA",
    "nome": "MARIA VALENTINA",
    "classe": "Gaseiro 7k",
    "ibe": 22.3,
    "ibeMedio": 17.8,
    "consumoReal": 48.9,
    "consumoIdeal": 40,
    "deltaFuelNm": 8.92,
    "emissoesCO2Perdidas": 10277.0,
    "riscoNormam401": "Alto",
    "statusOperacional": "Atracado",
    "diasDesdeUltimaLimpeza": 1167,
    "posicaoAtual": {
      "latitude": -1.422598,
      "longitude": -48.522415,
      "velocidade": 0.1,
      "rumo": 14.9,
      "dataHora": "2025-11-24 21:10:53"
    },
    "recomendacao": "Agendar Limpeza",
    "economiaAnual": 17663536.0,
    "eventosCriticos": 2,
    "eventosAlto": 5,
    "viagensAnalisadas": 30,
    "previsao30d": 22.9,
    "previsao60d": 23.4,
    "previsao90d": 24.0
  },
  {
    "id": "MARCOS_CAVALCANTI",
    "nome": "MARCOS CAVALCANTI",
    "classe": "MR 2",
    "ibe": 20.4,
    "ibeMedio": 16.3,
    "consumoReal": 48.2,
    "consumoIdeal": 40,
    "deltaFuelNm": 8.16,
    "emissoesCO2Perdidas": 9405.0,
    "riscoNormam401": "Alto",
    "statusOperacional": "Atracado",
    "diasDesdeUltimaLimpeza": 1026,
    "posicaoAtual": {
      "latitude": -23.759516,
      "longitude": -45.361216,
      "velocidade": 0.1,
      "rumo": 289.7,
      "dataHora": "2025-11-24 23:53:21"
    },
    "recomendacao": "Agendar Limpeza",
    "economiaAnual": 16165351.0,
    "eventosCriticos": 2,
    "eventosAlto": 5,
    "viagensAnalisadas": 30,
    "previsao30d": 21.0,
    "previsao60d": 21.6,
    "previsao90d": 22.2
  },
  {
    "id": "RAFAEL_SANTOS",
    "nome": "RAFAEL SANTOS",
    "classe": "Aframax",
    "ibe": 19.5,
    "ibeMedio": 15.6,
    "consumoReal": 47.8,
    "consumoIdeal": 40,
    "deltaFuelNm": 7.81,
    "emissoesCO2Perdidas": 9001.0,
    "riscoNormam401": "Alto",
    "statusOperacional": "Navegando",
    "diasDesdeUltimaLimpeza": 970,
    "posicaoAtual": {
      "latitude": -24.72482,
      "longitude": -37.137453,
      "velocidade": 10.9,
      "rumo": 100.6,
      "dataHora": "2025-10-05 05:18:15"
    },
    "recomendacao": "Agendar Limpeza",
    "economiaAnual": 15470906.0,
    "eventosCriticos": 1,
    "eventosAlto": 4,
    "viagensAnalisadas": 30,
    "previsao30d": 20.1,
    "previsao60d": 20.7,
    "previsao90d": 21.3
  },
  {
    "id": "RICARDO_BARBOSA",
    "nome": "RICARDO BARBOSA",
    "classe": "Gaseiro 7k",
    "ibe": 16.5,
    "ibeMedio": 13.2,
    "consumoReal": 46.6,
    "consumoIdeal": 40,
    "deltaFuelNm": 6.61,
    "emissoesCO2Perdidas": 7615.0,
    "riscoNormam401": "Alto",
    "statusOperacional": "Atracado",
    "diasDesdeUltimaLimpeza": 852,
    "posicaoAtual": {
      "latitude": -8.387865,
      "longitude": -34.909265,
      "velocidade": 0.8,
      "rumo": 183.0,
      "dataHora": "2025-11-24 20:37:31"
    },
    "recomendacao": "Agendar Limpeza",
    "economiaAnual": 13087534.0,
    "eventosCriticos": 1,
    "eventosAlto": 3,
    "viagensAnalisadas": 30,
    "previsao30d": 17.1,
    "previsao60d": 17.7,
    "previsao90d": 18.3
  },
  {
    "id": "RODRIGO_PINHEIRO",
    "nome": "RODRIGO PINHEIRO",
    "classe": "Suezmax",
    "ibe": 12.7,
    "ibeMedio": 10.2,
    "consumoReal": 45.1,
    "consumoIdeal": 40,
    "deltaFuelNm": 5.09,
    "emissoesCO2Perdidas": 5861.0,
    "riscoNormam401": "Medio",
    "statusOperacional": "Atracado",
    "diasDesdeUltimaLimpeza": 863,
    "posicaoAtual": {
      "latitude": -23.809498,
      "longitude": -45.387825,
      "velocidade": 0.0,
      "rumo": 264.9,
      "dataHora": "2025-11-23 10:45:23"
    },
    "recomendacao": "Monitorar",
    "economiaAnual": 10074399.0,
    "eventosCriticos": 0,
    "eventosAlto": 2,
    "viagensAnalisadas": 30,
    "previsao30d": 13.2,
    "previsao60d": 13.6,
    "previsao90d": 14.0
  },
  {
    "id": "ROMARIO_SILVA",
    "nome": "ROMARIO SILVA",
    "classe": "Aframax",
    "ibe": 12.2,
    "ibeMedio": 9.8,
    "consumoReal": 44.9,
    "consumoIdeal": 40,
    "deltaFuelNm": 4.88,
    "emissoesCO2Perdidas": 5619.0,
    "riscoNormam401": "Medio",
    "statusOperacional": "Navegando",
    "diasDesdeUltimaLimpeza": 803,
    "posicaoAtual": {
      "latitude": -22.872306,
      "longitude": -43.154943,
      "velocidade": 7.0,
      "rumo": 1.2,
      "dataHora": "2025-11-24 11:31:20"
    },
    "recomendacao": "Monitorar",
    "economiaAnual": 9657236.0,
    "eventosCriticos": 0,
    "eventosAlto": 2,
    "viagensAnalisadas": 30,
    "previsao30d": 12.6,
    "previsao60d": 13.1,
    "previsao90d": 13.6
  },
  {
    "id": "GABRIELA_MARTINS",
    "nome": "GABRIELA MARTINS",
    "classe": "MR 2",
    "ibe": 11.3,
    "ibeMedio": 9.0,
    "consumoReal": 44.5,
    "consumoIdeal": 40,
    "deltaFuelNm": 4.52,
    "emissoesCO2Perdidas": 5202.0,
    "riscoNormam401": "Medio",
    "statusOperacional": "Navegando",
    "diasDesdeUltimaLimpeza": 593,
    "posicaoAtual": {
      "latitude": -18.045911,
      "longitude": -37.769386,
      "velocidade": 12.1,
      "rumo": 17.1,
      "dataHora": "2025-11-24 21:47:17"
    },
    "recomendacao": "Monitorar",
    "economiaAnual": 8940366.0,
    "eventosCriticos": 0,
    "eventosAlto": 2,
    "viagensAnalisadas": 30,
    "previsao30d": 11.9,
    "previsao60d": 12.4,
    "previsao90d": 13.0
  },
  {
    "id": "EDUARDO_COSTA",
    "nome": "EDUARDO COSTA",
    "classe": "Gaseiro 7k",
    "ibe": 7.9,
    "ibeMedio": 6.3,
    "consumoReal": 43.1,
    "consumoIdeal": 40,
    "deltaFuelNm": 3.14,
    "emissoesCO2Perdidas": 3618.0,
    "riscoNormam401": "Medio",
    "statusOperacional": "Atracado",
    "diasDesdeUltimaLimpeza": 527,
    "posicaoAtual": {
      "latitude": -25.753498,
      "longitude": -48.152165,
      "velocidade": 0.2,
      "rumo": 38.8,
      "dataHora": "2025-11-24 11:30:36"
    },
    "recomendacao": "Monitorar",
    "economiaAnual": 6218490.0,
    "eventosCriticos": 0,
    "eventosAlto": 0,
    "viagensAnalisadas": 30,
    "previsao30d": 8.3,
    "previsao60d": 8.7,
    "previsao90d": 9.2
  },
  {
    "id": "VICTOR_OLIVEIRA",
    "nome": "VICTOR OLIVEIRA",
    "classe": "Gaseiro 7k",
    "ibe": 7.4,
    "ibeMedio": 5.9,
    "consumoReal": 43.0,
    "consumoIdeal": 40,
    "deltaFuelNm": 2.96,
    "emissoesCO2Perdidas": 3414.0,
    "riscoNormam401": "Medio",
    "statusOperacional": "Atracado",
    "diasDesdeUltimaLimpeza": 604,
    "posicaoAtual": {
      "latitude": -24.639211,
      "longitude": -42.41805,
      "velocidade": 0.0,
      "rumo": 160.4,
      "dataHora": "2025-11-24 23:56:58"
    },
    "recomendacao": "Monitorar",
    "economiaAnual": 5867406.0,
    "eventosCriticos": 0,
    "eventosAlto": 0,
    "viagensAnalisadas": 30,
    "previsao30d": 7.8,
    "previsao60d": 8.1,
    "previsao90d": 8.5
  },
  {
    "id": "GISELLE_CARVALHO",
    "nome": "GISELLE CARVALHO",
    "classe": "Gaseiro 7k",
    "ibe": 4.4,
    "ibeMedio": 3.5,
    "consumoReal": 41.7,
    "consumoIdeal": 40,
    "deltaFuelNm": 1.74,
    "emissoesCO2Perdidas": 2008.0,
    "riscoNormam401": "Baixo",
    "statusOperacional": "Atracado",
    "diasDesdeUltimaLimpeza": 348,
    "posicaoAtual": {
      "latitude": -23.917718,
      "longitude": -45.508033,
      "velocidade": 0.0,
      "rumo": 247.4,
      "dataHora": "2025-11-24 23:40:29"
    },
    "recomendacao": "OK",
    "economiaAnual": 3451051.0,
    "eventosCriticos": 0,
    "eventosAlto": 0,
    "viagensAnalisadas": 30,
    "previsao30d": 4.7,
    "previsao60d": 5.1,
    "previsao90d": 5.5
  },
  {
    "id": "BRUNO_LIMA",
    "nome": "BRUNO LIMA",
    "classe": "Suezmax",
    "ibe": 4.1,
    "ibeMedio": 3.3,
    "consumoReal": 41.6,
    "consumoIdeal": 40,
    "deltaFuelNm": 1.64,
    "emissoesCO2Perdidas": 1884.0,
    "riscoNormam401": "Baixo",
    "statusOperacional": "Atracado",
    "diasDesdeUltimaLimpeza": 354,
    "posicaoAtual": {
      "latitude": -8.393548,
      "longitude": -34.963065,
      "velocidade": 0.0,
      "rumo": 203.6,
      "dataHora": "2025-11-24 23:58:17"
    },
    "recomendacao": "OK",
    "economiaAnual": 3238664.0,
    "eventosCriticos": 0,
    "eventosAlto": 0,
    "viagensAnalisadas": 30,
    "previsao30d": 4.4,
    "previsao60d": 4.8,
    "previsao90d": 5.1
  },
  {
    "id": "RAUL_MARTINS",
    "nome": "RAUL MARTINS",
    "classe": "MR 2",
    "ibe": 3.7,
    "ibeMedio": 3.0,
    "consumoReal": 41.5,
    "consumoIdeal": 40,
    "deltaFuelNm": 1.49,
    "emissoesCO2Perdidas": 1711.0,
    "riscoNormam401": "Baixo",
    "statusOperacional": "Navegando",
    "diasDesdeUltimaLimpeza": 320,
    "posicaoAtual": {
      "latitude": -31.989313,
      "longitude": -45.621493,
      "velocidade": 11.5,
      "rumo": 89.4,
      "dataHora": "2025-10-04 18:58:17"
    },
    "recomendacao": "OK",
    "economiaAnual": 2941417.0,
    "eventosCriticos": 0,
    "eventosAlto": 0,
    "viagensAnalisadas": 30,
    "previsao30d": 4.1,
    "previsao60d": 4.4,
    "previsao90d": 4.8
  },
  {
    "id": "DANIEL_PEREIRA",
    "nome": "DANIEL PEREIRA",
    "classe": "MR 2",
    "ibe": 3.4,
    "ibeMedio": 2.7,
    "consumoReal": 41.4,
    "consumoIdeal": 40,
    "deltaFuelNm": 1.37,
    "emissoesCO2Perdidas": 1573.0,
    "riscoNormam401": "Baixo",
    "statusOperacional": "Navegando",
    "diasDesdeUltimaLimpeza": 409,
    "posicaoAtual": {
      "latitude": -1.182003,
      "longitude": -32.753965,
      "velocidade": 11.0,
      "rumo": 13.1,
      "dataHora": "2025-10-24 02:49:27"
    },
    "recomendacao": "OK",
    "economiaAnual": 2703801.0,
    "eventosCriticos": 0,
    "eventosAlto": 0,
    "viagensAnalisadas": 30,
    "previsao30d": 3.7,
    "previsao60d": 3.9,
    "previsao90d": 4.2
  },
  {
    "id": "THIAGO_FERNANDES",
    "nome": "THIAGO FERNANDES",
    "classe": "MR 2",
    "ibe": 2.0,
    "ibeMedio": 1.6,
    "consumoReal": 40.8,
    "consumoIdeal": 40,
    "deltaFuelNm": 0.78,
    "emissoesCO2Perdidas": 899.0,
    "riscoNormam401": "Baixo",
    "statusOperacional": "Navegando",
    "diasDesdeUltimaLimpeza": 291,
    "posicaoAtual": {
      "latitude": -8.496883,
      "longitude": -34.85338,
      "velocidade": 10.9,
      "rumo": 21.3,
      "dataHora": "2025-11-24 23:57:00"
    },
    "recomendacao": "OK",
    "economiaAnual": 1545944.0,
    "eventosCriticos": 0,
    "eventosAlto": 0,
    "viagensAnalisadas": 30,
    "previsao30d": 2.2,
    "previsao60d": 2.4,
    "previsao90d": 2.6
  },
  {
    "id": "FABIO_SANTOS",
    "nome": "FABIO SANTOS",
    "classe": "Suezmax",
    "ibe": 1.3,
    "ibeMedio": 1.1,
    "consumoReal": 40.5,
    "consumoIdeal": 40,
    "deltaFuelNm": 0.53,
    "emissoesCO2Perdidas": 611.0,
    "riscoNormam401": "Baixo",
    "statusOperacional": "Navegando",
    "diasDesdeUltimaLimpeza": 299,
    "posicaoAtual": {
      "latitude": -5.616115,
      "longitude": -35.000465,
      "velocidade": 12.5,
      "rumo": 355.0,
      "dataHora": "2025-11-24 22:22:42"
    },
    "recomendacao": "OK",
    "economiaAnual": 1050401.0,
    "eventosCriticos": 0,
    "eventosAlto": 0,
    "viagensAnalisadas": 30,
    "previsao30d": 1.5,
    "previsao60d": 1.6,
    "previsao90d": 1.7
  },
  {
    "id": "FELIPE_RIBEIRO",
    "nome": "FELIPE RIBEIRO",
    "classe": "Aframax",
    "ibe": 0.7,
    "ibeMedio": 0.5,
    "consumoReal": 40.3,
    "consumoIdeal": 40,
    "deltaFuelNm": 0.27,
    "emissoesCO2Perdidas": 316.0,
    "riscoNormam401": "Baixo",
    "statusOperacional": "Navegando",
    "diasDesdeUltimaLimpeza": 502,
    "posicaoAtual": {
      "latitude": -25.230053,
      "longitude": -37.859755,
      "velocidade": 12.6,
      "rumo": 99.0,
      "dataHora": "2025-10-10 23:20:36"
    },
    "recomendacao": "OK",
    "economiaAnual": 543894.0,
    "eventosCriticos": 0,
    "eventosAlto": 0,
    "viagensAnalisadas": 30,
    "previsao30d": 0.7,
    "previsao60d": 0.8,
    "previsao90d": 0.8
  },
  {
    "id": "LUCAS_MEDONCA",
    "nome": "LUCAS MEDONCA",
    "classe": "Aframax",
    "ibe": 0.1,
    "ibeMedio": 0.0,
    "consumoReal": 40.0,
    "consumoIdeal": 40,
    "deltaFuelNm": 0.02,
    "emissoesCO2Perdidas": 26.0,
    "riscoNormam401": "Baixo",
    "statusOperacional": "Navegando",
    "diasDesdeUltimaLimpeza": 457,
    "posicaoAtual": {
      "latitude": -15.446815,
      "longitude": -37.221481,
      "velocidade": 11.1,
      "rumo": 17.9,
      "dataHora": "2025-11-24 22:26:32"
    },
    "recomendacao": "OK",
    "economiaAnual": 44487.0,
    "eventosCriticos": 0,
    "eventosAlto": 0,
    "viagensAnalisadas": 30,
    "previsao30d": 0.1,
    "previsao60d": 0.1,
    "previsao90d": 0.1
  }
]